{
    "Meta Data": {
        "1. Information": "Weekly Prices and Volumes for Digital Currency",
        "2. Digital Currency Code": "BTC",
        "3. Digital Currency Name": "Bitcoin",
        "4. Market Code": "CNY",
        "5. Market Name": "Chinese Yuan",
        "6. Last Refreshed": "2017-12-05 (end of day)",
        "7. Time Zone": "UTC"
    },
    "Time Series (Digital Currency Weekly)": {
        "2017-12-05": {
            "1a. open (CNY)": "76189.51365940",
            "1b. open (USD)": "11495.18533780",
            "2a. high (CNY)": "77739.71477000",
            "2b. high (USD)": "11756.12303140",
            "3a. low (CNY)": "69121.69728620",
            "3b. low (USD)": "10444.30892600",
            "4a. close (CNY)": "69136.48584560",
            "4b. close (USD)": "10444.80068970",
            "5. volume": "0.64211000",
            "6. market cap (USD)": "6928.89498953"
        },
        "2017-12-03": {
            "1a. open (CNY)": "60758.77875000",
            "1b. open (USD)": "9286.07347547",
            "2a. high (CNY)": "76209.12071750",
            "2b. high (USD)": "11516.47485680",
            "3a. low (CNY)": "60758.77875000",
            "3b. low (USD)": "9285.40880693",
            "4a. close (CNY)": "76189.51365940",
            "4b. close (USD)": "11495.18533780",
            "5. volume": "3.41543693",
            "6. market cap (USD)": "36176.43509660"
        },
        "2017-11-26": {
            "1a. open (CNY)": "53445.00000000",
            "1b. open (USD)": "8027.54705078",
            "2a. high (CNY)": "61296.00150000",
            "2b. high (USD)": "9373.26556515",
            "3a. low (CNY)": "52300.27969000",
            "3b. low (USD)": "7939.32139507",
            "4a. close (CNY)": "60758.77875000",
            "4b. close (USD)": "9286.07347547",
            "5. volume": "2.35053000",
            "6. market cap (USD)": "19495.74054440"
        },
        "2017-11-19": {
            "1a. open (CNY)": "44169.53149130",
            "1b. open (USD)": "6653.64116222",
            "2a. high (CNY)": "53565.79000000",
            "2b. high (USD)": "8077.72080889",
            "3a. low (CNY)": "44168.34050960",
            "3b. low (USD)": "6645.36600536",
            "4a. close (CNY)": "53445.00000000",
            "4b. close (USD)": "8027.54705078",
            "5. volume": "3.12073497",
            "6. market cap (USD)": "23930.44625630"
        },
        "2017-11-12": {
            "1a. open (CNY)": "50004.89000000",
            "1b. open (USD)": "7548.64854665",
            "2a. high (CNY)": "50612.14484690",
            "2b. high (USD)": "7637.29060246",
            "3a. low (CNY)": "44154.10359410",
            "3b. low (USD)": "6648.46280355",
            "4a. close (CNY)": "44169.53149130",
            "4b. close (USD)": "6653.64116222",
            "5. volume": "22.49479178",
            "6. market cap (USD)": "159847.55661900"
        },
        "2017-11-05": {
            "1a. open (CNY)": "37503.55971850",
            "1b. open (USD)": "5632.43368905",
            "2a. high (CNY)": "50785.89758990",
            "2b. high (USD)": "7662.71154442",
            "3a. low (CNY)": "37319.42551710",
            "3b. low (USD)": "5605.03221849",
            "4a. close (CNY)": "50004.89000000",
            "4b. close (USD)": "7548.64854665",
            "5. volume": "11698.46546110",
            "6. market cap (USD)": "69312004.77429999"
        },
        "2017-10-29": {
            "1a. open (CNY)": "37343.54020950",
            "1b. open (USD)": "5629.53798289",
            "2a. high (CNY)": "37725.35411130",
            "2b. high (USD)": "5666.80410360",
            "3a. low (CNY)": "33959.57042270",
            "3b. low (USD)": "5112.85311994",
            "4a. close (CNY)": "37658.87184300",
            "4b. close (USD)": "5655.75908132",
            "5. volume": "32936.09142580",
            "6. market cap (USD)": "178813132.31500000"
        },
        "2017-10-22": {
            "1a. open (CNY)": "36684.87242250",
            "1b. open (USD)": "5570.21400607",
            "2a. high (CNY)": "38387.63397460",
            "2b. high (USD)": "5795.84708145",
            "3a. low (CNY)": "33193.14469400",
            "3b. low (USD)": "5008.32046200",
            "4a. close (CNY)": "37357.99490050",
            "4b. close (USD)": "5631.71702729",
            "5. volume": "34413.97742270",
            "6. market cap (USD)": "189903213.44700000"
        },
        "2017-10-15": {
            "1a. open (CNY)": "29216.53686050",
            "1b. open (USD)": "4393.19993692",
            "2a. high (CNY)": "38472.91904320",
            "2b. high (USD)": "5850.94514311",
            "3a. low (CNY)": "28890.78577940",
            "3b. low (USD)": "4352.37901693",
            "4a. close (CNY)": "36651.66400570",
            "4b. close (USD)": "5565.17165546",
            "5. volume": "46729.96620280",
            "6. market cap (USD)": "242598926.60299999"
        },
        "2017-10-08": {
            "1a. open (CNY)": "27498.35203760",
            "1b. open (USD)": "4129.99790297",
            "2a. high (CNY)": "29456.50459090",
            "2b. high (USD)": "4426.52089036",
            "3a. low (CNY)": "26884.31182550",
            "3b. low (USD)": "4040.58146568",
            "4a. close (CNY)": "29228.96275410",
            "4b. close (USD)": "4395.06837996",
            "5. volume": "47746.00488000",
            "6. market cap (USD)": "198755207.48199999"
        },
        "2017-10-01": {
            "1a. open (CNY)": "22293.86673470",
            "1b. open (USD)": "3373.64154423",
            "2a. high (CNY)": "27483.30827550",
            "2b. high (USD)": "4127.73846919",
            "3a. low (CNY)": "22270.86043400",
            "3b. low (USD)": "3372.07365191",
            "4a. close (CNY)": "27470.61115260",
            "4b. close (USD)": "4125.83147887",
            "5. volume": "91411.06037810",
            "6. market cap (USD)": "343702994.75599998"
        },
        "2017-09-24": {
            "1a. open (CNY)": "19966.45956050",
            "1b. open (USD)": "3050.53923457",
            "2a. high (CNY)": "24093.63742550",
            "2b. high (USD)": "3658.70393702",
            "3a. low (CNY)": "19966.45956050",
            "3b. low (USD)": "3050.53923457",
            "4a. close (CNY)": "22291.02208350",
            "4b. close (USD)": "3373.21107456",
            "5. volume": "168499.47922500",
            "6. market cap (USD)": "589633929.64800000"
        },
        "2017-09-17": {
            "1a. open (CNY)": "23447.57894840",
            "1b. open (USD)": "3589.46418668",
            "2a. high (CNY)": "27432.36691570",
            "2b. high (USD)": "4200.85086546",
            "3a. low (CNY)": "16703.05615130",
            "3b. low (USD)": "2552.16638536",
            "4a. close (CNY)": "19920.90060080",
            "4b. close (USD)": "3043.57859172",
            "5. volume": "656314.01290700",
            "6. market cap (USD)": "2144230229.57999992"
        },
        "2017-09-10": {
            "1a. open (CNY)": "28599.38214560",
            "1b. open (USD)": "4367.86297467",
            "2a. high (CNY)": "29202.98862350",
            "2b. high (USD)": "4496.38326444",
            "3a. low (CNY)": "21892.06326890",
            "3b. low (USD)": "3377.51874800",
            "4a. close (CNY)": "23349.72883370",
            "4b. close (USD)": "3574.48483708",
            "5. volume": "623327.83965300",
            "6. market cap (USD)": "2470163202.73000002"
        },
        "2017-09-03": {
            "1a. open (CNY)": "28866.01127750",
            "1b. open (USD)": "4386.99847680",
            "2a. high (CNY)": "32186.28627160",
            "2b. high (USD)": "4905.51133879",
            "3a. low (CNY)": "27691.69733520",
            "3b. low (USD)": "4168.75041686",
            "4a. close (CNY)": "28538.69069030",
            "4b. close (USD)": "4358.59382476",
            "5. volume": "390044.35917800",
            "6. market cap (USD)": "1758986901.53999996"
        },
        "2017-08-27": {
            "1a. open (CNY)": "27618.09845080",
            "1b. open (USD)": "4140.35517920",
            "2a. high (CNY)": "29415.79096450",
            "2b. high (USD)": "4418.41937900",
            "3a. low (CNY)": "25118.67228280",
            "3b. low (USD)": "3772.69629314",
            "4a. close (CNY)": "28883.81770680",
            "4b. close (USD)": "4389.70466220",
            "5. volume": "354536.55383000",
            "6. market cap (USD)": "1491018735.85999990"
        },
        "2017-08-20": {
            "1a. open (CNY)": "27256.28182150",
            "1b. open (USD)": "4090.84564504",
            "2a. high (CNY)": "30133.77350420",
            "2b. high (USD)": "4513.75895025",
            "3a. low (CNY)": "26746.11173140",
            "3b. low (USD)": "4002.47631894",
            "4a. close (CNY)": "27575.43609120",
            "4b. close (USD)": "4133.95947017",
            "5. volume": "538254.17957000",
            "6. market cap (USD)": "2298262263.98000002"
        },
        "2017-08-13": {
            "1a. open (CNY)": "21418.00944980",
            "1b. open (USD)": "3166.82208255",
            "2a. high (CNY)": "28001.69398990",
            "2b. high (USD)": "4201.49353908",
            "3a. low (CNY)": "21316.71905620",
            "3b. low (USD)": "3166.82208255",
            "4a. close (CNY)": "27294.78646120",
            "4b. close (USD)": "4096.62473621",
            "5. volume": "431282.90497600",
            "6. market cap (USD)": "1586460182.07999992"
        },
        "2017-08-06": {
            "1a. open (CNY)": "18639.73643170",
            "1b. open (USD)": "2767.53305708",
            "2a. high (CNY)": "22396.57111260",
            "2b. high (USD)": "3326.88222113",
            "3a. low (CNY)": "17917.37712210",
            "3b. low (USD)": "2666.95936893",
            "4a. close (CNY)": "21424.23292790",
            "4b. close (USD)": "3167.74227301",
            "5. volume": "429544.85885800",
            "6. market cap (USD)": "1262864431.98000002"
        },
        "2017-07-30": {
            "1a. open (CNY)": "18183.42682140",
            "1b. open (USD)": "2704.51523136",
            "2a. high (CNY)": "19316.83615510",
            "2b. high (USD)": "2864.72432969",
            "3a. low (CNY)": "16527.85349870",
            "3b. low (USD)": "2445.32639341",
            "4a. close (CNY)": "18639.82578340",
            "4b. close (USD)": "2767.54632355",
            "5. volume": "325284.00630700",
            "6. market cap (USD)": "879689837.85399997"
        },
        "2017-07-23": {
            "1a. open (CNY)": "13351.06361100",
            "1b. open (USD)": "1979.84186417",
            "2a. high (CNY)": "19642.55757500",
            "2b. high (USD)": "2906.11218662",
            "3a. low (CNY)": "13351.06361100",
            "3b. low (USD)": "1976.15665502",
            "4a. close (CNY)": "18120.46769770",
            "4b. close (USD)": "2695.15099487",
            "5. volume": "456506.02708400",
            "6. market cap (USD)": "1181862576.49000001"
        },
        "2017-07-16": {
            "1a. open (CNY)": "17554.48547550",
            "1b. open (USD)": "2579.89502224",
            "2a. high (CNY)": "17610.96425070",
            "2b. high (USD)": "2588.70560792",
            "3a. low (CNY)": "12981.23577450",
            "3b. low (USD)": "1915.21562928",
            "4a. close (CNY)": "13337.99041000",
            "4b. close (USD)": "1977.90322681",
            "5. volume": "294121.02667200",
            "6. market cap (USD)": "666231802.77100003"
        },
        "2017-07-09": {
            "1a. open (CNY)": "17326.20052460",
            "1b. open (USD)": "2556.09001013",
            "2a. high (CNY)": "18448.03417290",
            "2b. high (USD)": "2712.66895118",
            "3a. low (CNY)": "17064.07789040",
            "3b. low (USD)": "2507.63468561",
            "4a. close (CNY)": "17541.82243960",
            "4b. close (USD)": "2578.03399911",
            "5. volume": "204037.99031100",
            "6. market cap (USD)": "536843847.50099999"
        },
        "2017-07-02": {
            "1a. open (CNY)": "19731.01844330",
            "1b. open (USD)": "2887.12106748",
            "2a. high (CNY)": "19744.82879120",
            "2b. high (USD)": "2898.57949318",
            "3a. low (CNY)": "16715.62745500",
            "3b. low (USD)": "2454.00545087",
            "4a. close (CNY)": "17361.43516100",
            "4b. close (USD)": "2561.28808584",
            "5. volume": "256836.21328300",
            "6. market cap (USD)": "677946293.32200003"
        },
        "2017-06-25": {
            "1a. open (CNY)": "18860.19724970",
            "1b. open (USD)": "2771.27619163",
            "2a. high (CNY)": "20368.46469100",
            "2b. high (USD)": "2982.55501245",
            "3a. low (CNY)": "18612.34994490",
            "3b. low (USD)": "2722.41724002",
            "4a. close (CNY)": "19693.46427700",
            "4b. close (USD)": "2881.62599255",
            "5. volume": "324598.99136500",
            "6. market cap (USD)": "933112341.17900002"
        },
        "2017-06-18": {
            "1a. open (CNY)": "20827.09654850",
            "1b. open (USD)": "3070.57506465",
            "2a. high (CNY)": "20999.47178310",
            "2b. high (USD)": "3094.30071217",
            "3a. low (CNY)": "16914.44976680",
            "3b. low (USD)": "2484.81446193",
            "4a. close (CNY)": "18855.19915640",
            "4b. close (USD)": "2770.54178271",
            "5. volume": "393890.71776100",
            "6. market cap (USD)": "1079727158.32999992"
        },
        "2017-06-11": {
            "1a. open (CNY)": "17678.02369550",
            "1b. open (USD)": "2594.87526700",
            "2a. high (CNY)": "21016.43457920",
            "2b. high (USD)": "3091.47047442",
            "3a. low (CNY)": "17627.50574200",
            "3b. low (USD)": "2587.28641291",
            "4a. close (CNY)": "20805.34979460",
            "4b. close (USD)": "3067.36890290",
            "5. volume": "332776.74806900",
            "6. market cap (USD)": "960863205.35099995"
        },
        "2017-06-04": {
            "1a. open (CNY)": "14672.91042450",
            "1b. open (USD)": "2140.70317043",
            "2a. high (CNY)": "17841.59862300",
            "2b. high (USD)": "2618.98870046",
            "3a. low (CNY)": "14047.19175230",
            "3b. low (USD)": "2048.03184424",
            "4a. close (CNY)": "17612.44900390",
            "4b. close (USD)": "2585.24986156",
            "5. volume": "345107.78934800",
            "6. market cap (USD)": "845851352.84800005"
        },
        "2017-05-28": {
            "1a. open (CNY)": "13630.53966260",
            "1b. open (USD)": "1988.62598571",
            "2a. high (CNY)": "19047.42272970",
            "2b. high (USD)": "2772.67169304",
            "3a. low (CNY)": "12415.21660530",
            "3b. low (USD)": "1811.62052287",
            "4a. close (CNY)": "14633.20078120",
            "4b. close (USD)": "2134.90973499",
            "5. volume": "602119.39037300",
            "6. market cap (USD)": "1340016809.50000000"
        },
        "2017-05-21": {
            "1a. open (CNY)": "10782.10981940",
            "1b. open (USD)": "1561.66045592",
            "2a. high (CNY)": "14003.32304450",
            "2b. high (USD)": "2034.49437298",
            "3a. low (CNY)": "9585.61910178",
            "3b. low (USD)": "1390.43064038",
            "4a. close (CNY)": "13636.02805300",
            "4b. close (USD)": "1989.42671379",
            "5. volume": "304977.50345300",
            "6. market cap (USD)": "517906900.24500000"
        },
        "2017-05-14": {
            "1a. open (CNY)": "8707.05465952",
            "1b. open (USD)": "1267.28455090",
            "2a. high (CNY)": "10987.37126870",
            "2b. high (USD)": "1592.24042245",
            "3a. low (CNY)": "8707.05465952",
            "3b. low (USD)": "1263.05048391",
            "4a. close (CNY)": "10789.76516930",
            "4b. close (USD)": "1562.76924237",
            "5. volume": "360048.24692200",
            "6. market cap (USD)": "530299654.83800000"
        },
        "2017-05-07": {
            "1a. open (CNY)": "8056.63902681",
            "1b. open (USD)": "1165.76294794",
            "2a. high (CNY)": "9334.99752555",
            "2b. high (USD)": "1352.52575748",
            "3a. low (CNY)": "8056.63902681",
            "3b. low (USD)": "1165.76294794",
            "4a. close (CNY)": "8706.96240138",
            "4b. close (USD)": "1267.27112302",
            "5. volume": "301763.50049000",
            "6. market cap (USD)": "380559804.42900002"
        },
        "2017-04-30": {
            "1a. open (CNY)": "7142.97968493",
            "1b. open (USD)": "1051.78369872",
            "2a. high (CNY)": "8061.38356958",
            "2b. high (USD)": "1166.44946402",
            "3a. low (CNY)": "7139.37484152",
            "3b. low (USD)": "1040.22638564",
            "4a. close (CNY)": "8061.38356958",
            "4b. close (USD)": "1166.44946402",
            "5. volume": "167472.97144900",
            "6. market cap (USD)": "186989060.65200001"
        },
        "2017-04-23": {
            "1a. open (CNY)": "7133.69203859",
            "1b. open (USD)": "1034.80948813",
            "2a. high (CNY)": "7432.52243328",
            "2b. high (USD)": "1080.22998812",
            "3a. low (CNY)": "7046.54744656",
            "3b. low (USD)": "1023.10332912",
            "4a. close (CNY)": "7143.22236215",
            "4b. close (USD)": "1051.81943226",
            "5. volume": "125393.33102800",
            "6. market cap (USD)": "131745876.23899999"
        },
        "2017-04-16": {
            "1a. open (CNY)": "7274.45790883",
            "1b. open (USD)": "1053.24715448",
            "2a. high (CNY)": "7417.79383356",
            "2b. high (USD)": "1075.90705250",
            "3a. low (CNY)": "7021.48509034",
            "3b. low (USD)": "1020.95794024",
            "4a. close (CNY)": "7138.85451296",
            "4b. close (USD)": "1035.55835386",
            "5. volume": "95495.33302860",
            "6. market cap (USD)": "100321865.66200000"
        },
        "2017-04-09": {
            "1a. open (CNY)": "6950.46923138",
            "1b. open (USD)": "1010.25392746",
            "2a. high (CNY)": "7345.20628037",
            "2b. high (USD)": "1063.86736870",
            "3a. low (CNY)": "6939.83842659",
            "3b. low (USD)": "1008.52154080",
            "4a. close (CNY)": "7270.98376472",
            "4b. close (USD)": "1052.74414347",
            "5. volume": "145449.97310100",
            "6. market cap (USD)": "150454644.56099999"
        },
        "2017-04-02": {
            "1a. open (CNY)": "6701.93038127",
            "1b. open (USD)": "977.97638813",
            "2a. high (CNY)": "7083.60717705",
            "2b. high (USD)": "1028.16688710",
            "3a. low (CNY)": "6644.31813013",
            "3b. low (USD)": "968.98579144",
            "4a. close (CNY)": "6955.56804539",
            "4b. close (USD)": "1010.99504244",
            "5. volume": "190619.46032100",
            "6. market cap (USD)": "191194289.01600000"
        },
        "2017-03-26": {
            "1a. open (CNY)": "7140.57308578",
            "1b. open (USD)": "1034.10132884",
            "2a. high (CNY)": "7500.82831976",
            "2b. high (USD)": "1089.44745838",
            "3a. low (CNY)": "6205.65202181",
            "3b. low (USD)": "902.25970453",
            "4a. close (CNY)": "6701.14178681",
            "4b. close (USD)": "977.86131281",
            "5. volume": "194460.84755400",
            "6. market cap (USD)": "194596350.98300001"
        },
        "2017-03-19": {
            "1a. open (CNY)": "8120.15765240",
            "1b. open (USD)": "1182.69650331",
            "2a. high (CNY)": "8247.98862275",
            "2b. high (USD)": "1196.67336862",
            "3a. low (CNY)": "6732.84331586",
            "3b. low (USD)": "976.31915139",
            "4a. close (CNY)": "7151.81672246",
            "4b. close (USD)": "1035.72963787",
            "5. volume": "221662.37410600",
            "6. market cap (USD)": "238510608.53700000"
        },
        "2017-03-12": {
            "1a. open (CNY)": "8467.73271264",
            "1b. open (USD)": "1227.11871787",
            "2a. high (CNY)": "8498.52682560",
            "2b. high (USD)": "1239.31214878",
            "3a. low (CNY)": "7498.01417731",
            "3b. low (USD)": "1084.64091442",
            "4a. close (CNY)": "8120.05807771",
            "4b. close (USD)": "1182.68200031",
            "5. volume": "255714.61669000",
            "6. market cap (USD)": "292680227.39700001"
        },
        "2017-03-05": {
            "1a. open (CNY)": "7865.05442040",
            "1b. open (USD)": "1140.47451828",
            "2a. high (CNY)": "8526.14174737",
            "2b. high (USD)": "1236.49704838",
            "3a. low (CNY)": "7850.76465109",
            "3b. low (USD)": "1137.47249701",
            "4a. close (CNY)": "8468.11042455",
            "4b. close (USD)": "1227.17345476",
            "5. volume": "212247.88506100",
            "6. market cap (USD)": "253408939.87799999"
        },
        "2017-02-26": {
            "1a. open (CNY)": "7113.13298864",
            "1b. open (USD)": "1037.15687395",
            "2a. high (CNY)": "8064.69966142",
            "2b. high (USD)": "1174.15733587",
            "3a. low (CNY)": "7058.61303253",
            "3b. low (USD)": "1027.71638081",
            "4a. close (CNY)": "7866.36548013",
            "4b. close (USD)": "1140.66462888",
            "5. volume": "222798.68793100",
            "6. market cap (USD)": "250057583.18799999"
        },
        "2017-02-19": {
            "1a. open (CNY)": "6792.93804584",
            "1b. open (USD)": "986.29913694",
            "2a. high (CNY)": "7221.58087751",
            "2b. high (USD)": "1051.71206255",
            "3a. low (CNY)": "6566.93211733",
            "3b. low (USD)": "954.33795442",
            "4a. close (CNY)": "7110.92890605",
            "4b. close (USD)": "1036.83549948",
            "5. volume": "175555.69961100",
            "6. market cap (USD)": "175579667.11500001"
        },
        "2017-02-12": {
            "1a. open (CNY)": "7213.77466597",
            "1b. open (USD)": "1050.06413044",
            "2a. high (CNY)": "7594.93127259",
            "2b. high (USD)": "1105.69623936",
            "3a. low (CNY)": "6336.12574199",
            "3b. low (USD)": "920.45349768",
            "4a. close (CNY)": "6789.65395452",
            "4b. close (USD)": "985.82230403",
            "5. volume": "685443.33103500",
            "6. market cap (USD)": "703934365.11600006"
        },
        "2017-02-05": {
            "1a. open (CNY)": "6366.93850819",
            "1b. open (USD)": "925.34640993",
            "2a. high (CNY)": "7301.33214474",
            "2b. high (USD)": "1062.64567156",
            "3a. low (CNY)": "6347.83796896",
            "3b. low (USD)": "922.42294331",
            "4a. close (CNY)": "7211.02236518",
            "4b. close (USD)": "1049.66349520",
            "5. volume": "731622.30746000",
            "6. market cap (USD)": "739641238.94500005"
        },
        "2017-01-29": {
            "1a. open (CNY)": "6385.96293885",
            "1b. open (USD)": "928.67822390",
            "2a. high (CNY)": "6416.60739966",
            "2b. high (USD)": "936.71049534",
            "3a. low (CNY)": "6188.92447140",
            "3b. low (USD)": "900.85347438",
            "4a. close (CNY)": "6365.28604476",
            "4b. close (USD)": "925.10624724",
            "5. volume": "1093320.44018000",
            "6. market cap (USD)": "1004576839.58000004"
        },
        "2017-01-22": {
            "1a. open (CNY)": "5585.63154865",
            "1b. open (USD)": "809.50008676",
            "2a. high (CNY)": "6513.26995171",
            "2b. high (USD)": "947.19183755",
            "3a. low (CNY)": "5556.27113099",
            "3b. low (USD)": "805.26252089",
            "4a. close (CNY)": "6380.89414526",
            "4b. close (USD)": "927.94109494",
            "5. volume": "4353931.50152000",
            "6. market cap (USD)": "3882890407.84000015"
        },
        "2017-01-15": {
            "1a. open (CNY)": "6357.88657241",
            "1b. open (USD)": "919.00878442",
            "2a. high (CNY)": "6431.23839803",
            "2b. high (USD)": "928.72550803",
            "3a. low (CNY)": "4944.83539139",
            "3b. low (USD)": "712.81016439",
            "4a. close (CNY)": "5571.57587288",
            "4b. close (USD)": "807.46306182",
            "5. volume": "17436084.63120000",
            "6. market cap (USD)": "14502279187.29999924"
        },
        "2017-01-08": {
            "1a. open (CNY)": "7172.14689762",
            "1b. open (USD)": "1032.75114801",
            "2a. high (CNY)": "8896.43065739",
            "2b. high (USD)": "1285.83944835",
            "3a. low (CNY)": "5692.87356412",
            "3b. low (USD)": "822.84795319",
            "4a. close (CNY)": "6355.16704848",
            "4b. close (USD)": "918.61568739",
            "5. volume": "43819733.88290000",
            "6. market cap (USD)": "44251940639.19999695"
        },
        "2017-01-01": {
            "1a. open (CNY)": "6362.17342247",
            "1b. open (USD)": "915.90824215",
            "2a. high (CNY)": "7195.98116174",
            "2b. high (USD)": "1036.16650145",
            "3a. low (CNY)": "6362.17342247",
            "3b. low (USD)": "915.90824215",
            "4a. close (CNY)": "7166.22647589",
            "4b. close (USD)": "1031.89863866",
            "5. volume": "27726560.86990000",
            "6. market cap (USD)": "27177313586.00000000"
        },
        "2016-12-25": {
            "1a. open (CNY)": "5569.97851897",
            "1b. open (USD)": "800.37626724",
            "2a. high (CNY)": "6582.43960662",
            "2b. high (USD)": "947.61809980",
            "3a. low (CNY)": "5562.99635481",
            "3b. low (USD)": "800.07426253",
            "4a. close (CNY)": "6350.01291052",
            "4b. close (USD)": "914.15759621",
            "5. volume": "31169575.50940000",
            "6. market cap (USD)": "27751399886.70000076"
        },
        "2016-12-18": {
            "1a. open (CNY)": "5376.60715454",
            "1b. open (USD)": "778.55304742",
            "2a. high (CNY)": "5593.46424353",
            "2b. high (USD)": "803.75104086",
            "3a. low (CNY)": "5365.67099276",
            "3b. low (USD)": "777.57915936",
            "4a. close (CNY)": "5572.84507099",
            "4b. close (USD)": "800.78817551",
            "5. volume": "18289876.72530000",
            "6. market cap (USD)": "14485206563.79999924"
        },
        "2016-12-11": {
            "1a. open (CNY)": "5454.82361345",
            "1b. open (USD)": "792.86114299",
            "2a. high (CNY)": "5463.85412500",
            "2b. high (USD)": "794.18758430",
            "3a. low (CNY)": "5241.52983084",
            "3b. low (USD)": "761.47063758",
            "4a. close (CNY)": "5367.19630716",
            "4b. close (USD)": "777.19032114",
            "5. volume": "23760355.04880000",
            "6. market cap (USD)": "18443446967.00000000"
        },
        "2016-12-04": {
            "1a. open (CNY)": "5152.84860386",
            "1b. open (USD)": "744.70878529",
            "2a. high (CNY)": "5508.41591835",
            "2b. high (USD)": "799.78742453",
            "3a. low (CNY)": "5145.56391593",
            "3b. low (USD)": "744.46475030",
            "4a. close (CNY)": "5452.08163107",
            "4b. close (USD)": "792.46259458",
            "5. volume": "18884878.94590000",
            "6. market cap (USD)": "14635881309.79999924"
        },
        "2016-11-27": {
            "1a. open (CNY)": "5129.06059268",
            "1b. open (USD)": "744.61908265",
            "2a. high (CNY)": "5341.88759833",
            "2b. high (USD)": "775.32420008",
            "3a. low (CNY)": "5094.96028205",
            "3b. low (USD)": "737.32467744",
            "4a. close (CNY)": "5148.97409308",
            "4b. close (USD)": "744.14882662",
            "5. volume": "18282412.96100000",
            "6. market cap (USD)": "13766431690.70000076"
        },
        "2016-11-20": {
            "1a. open (CNY)": "4805.69834117",
            "1b. open (USD)": "705.31521118",
            "2a. high (CNY)": "5388.90626025",
            "2b. high (USD)": "787.73445819",
            "3a. low (CNY)": "4784.61131085",
            "3b. low (USD)": "702.28630904",
            "4a. close (CNY)": "5124.82717085",
            "4b. close (USD)": "744.00448927",
            "5. volume": "29417182.84990000",
            "6. market cap (USD)": "22125726577.90000153"
        },
        "2016-11-13": {
            "1a. open (CNY)": "4817.46580499",
            "1b. open (USD)": "712.88921808",
            "2a. high (CNY)": "4984.37171153",
            "2b. high (USD)": "735.94242352",
            "3a. low (CNY)": "4691.72747308",
            "3b. low (USD)": "688.58407078",
            "4a. close (CNY)": "4803.87559877",
            "4b. close (USD)": "705.04769377",
            "5. volume": "22349281.81160000",
            "6. market cap (USD)": "15994762131.50000000"
        },
        "2016-11-06": {
            "1a. open (CNY)": "4810.09006144",
            "1b. open (USD)": "712.44191507",
            "2a. high (CNY)": "5129.79978051",
            "2b. high (USD)": "758.93211871",
            "3a. low (CNY)": "4553.59419105",
            "3b. low (USD)": "673.37611408",
            "4a. close (CNY)": "4818.46779861",
            "4b. close (USD)": "713.03749322",
            "5. volume": "27470149.51470000",
            "6. market cap (USD)": "19514585028.70000076"
        },
        "2016-10-30": {
            "1a. open (CNY)": "4499.11808308",
            "1b. open (USD)": "665.04817638",
            "2a. high (CNY)": "4941.09512984",
            "2b. high (USD)": "729.05004584",
            "3a. low (CNY)": "4461.15028871",
            "3b. low (USD)": "658.14751932",
            "4a. close (CNY)": "4818.06482793",
            "4b. close (USD)": "713.62309002",
            "5. volume": "19724955.69970000",
            "6. market cap (USD)": "13773177441.89999962"
        },
        "2016-10-23": {
            "1a. open (CNY)": "4337.74779615",
            "1b. open (USD)": "644.60149722",
            "2a. high (CNY)": "4564.37067643",
            "2b. high (USD)": "674.86702642",
            "3a. low (CNY)": "4232.20040530",
            "3b. low (USD)": "628.08999565",
            "4a. close (CNY)": "4503.92639148",
            "4b. close (USD)": "665.75892828",
            "5. volume": "8463619.25264000",
            "6. market cap (USD)": "5492446114.93999958"
        },
        "2016-10-16": {
            "1a. open (CNY)": "4113.18316648",
            "1b. open (USD)": "616.23463493",
            "2a. high (CNY)": "4355.73025029",
            "2b. high (USD)": "647.38341179",
            "3a. low (CNY)": "4113.18316648",
            "3b. low (USD)": "615.58765122",
            "4a. close (CNY)": "4337.69771416",
            "4b. close (USD)": "644.59405490",
            "5. volume": "7515141.38439000",
            "6. market cap (USD)": "4811262337.03999996"
        },
        "2016-10-09": {
            "1a. open (CNY)": "4084.07459805",
            "1b. open (USD)": "613.46224588",
            "2a. high (CNY)": "4133.64761615",
            "2b. high (USD)": "619.59338321",
            "3a. low (CNY)": "4063.49264292",
            "3b. low (USD)": "609.07053478",
            "4a. close (CNY)": "4113.02321572",
            "4b. close (USD)": "616.21067120",
            "5. volume": "3850188.65848000",
            "6. market cap (USD)": "2366913699.94999981"
        },
        "2016-10-02": {
            "1a. open (CNY)": "3992.45694078",
            "1b. open (USD)": "598.89159844",
            "2a. high (CNY)": "4107.50521978",
            "2b. high (USD)": "615.83043069",
            "3a. low (CNY)": "3990.38652008",
            "3b. low (USD)": "598.66184584",
            "4a. close (CNY)": "4083.93198376",
            "4b. close (USD)": "613.44082402",
            "5. volume": "4532270.33009000",
            "6. market cap (USD)": "2759041621.53999996"
        },
        "2016-09-25": {
            "1a. open (CNY)": "4060.15089753",
            "1b. open (USD)": "608.48181599",
            "2a. high (CNY)": "4075.76084411",
            "2b. high (USD)": "609.77143566",
            "3a. low (CNY)": "3943.92612429",
            "3b. low (USD)": "590.94782889",
            "4a. close (CNY)": "3994.12058084",
            "4b. close (USD)": "599.14115406",
            "5. volume": "4328095.48103000",
            "6. market cap (USD)": "2601630568.46999979"
        },
        "2016-09-18": {
            "1a. open (CNY)": "4037.59654821",
            "1b. open (USD)": "603.82408512",
            "2a. high (CNY)": "4069.07184616",
            "2b. high (USD)": "609.88000851",
            "3a. low (CNY)": "4019.61048004",
            "3b. low (USD)": "601.56771167",
            "4a. close (CNY)": "4060.43463239",
            "4b. close (USD)": "608.52433843",
            "5. volume": "4182827.50255000",
            "6. market cap (USD)": "2534616353.59999990"
        },
        "2016-09-11": {
            "1a. open (CNY)": "4105.83196610",
            "1b. open (USD)": "614.54541028",
            "2a. high (CNY)": "4198.76057076",
            "2b. high (USD)": "628.43373092",
            "3a. low (CNY)": "3953.60127077",
            "3b. low (USD)": "591.74043275",
            "4a. close (CNY)": "4030.86502294",
            "4b. close (USD)": "602.81738298",
            "5. volume": "4213695.34046000",
            "6. market cap (USD)": "2588310266.96999979"
        },
        "2016-09-04": {
            "1a. open (CNY)": "3829.66398206",
            "1b. open (USD)": "573.85193052",
            "2a. high (CNY)": "4121.42798081",
            "2b. high (USD)": "616.85575737",
            "3a. low (CNY)": "3816.03277772",
            "3b. low (USD)": "571.40267636",
            "4a. close (CNY)": "4105.49540986",
            "4b. close (USD)": "614.49503582",
            "5. volume": "3006171.14737000",
            "6. market cap (USD)": "1766342231.46000004"
        },
        "2016-08-28": {
            "1a. open (CNY)": "3877.63628842",
            "1b. open (USD)": "584.60330213",
            "2a. high (CNY)": "3931.56508932",
            "2b. high (USD)": "591.71588736",
            "3a. low (CNY)": "3772.13990160",
            "3b. low (USD)": "565.67603076",
            "4a. close (CNY)": "3824.33078367",
            "4b. close (USD)": "573.05278308",
            "5. volume": "2706919.73017000",
            "6. market cap (USD)": "1564453992.99000001"
        },
        "2016-08-21": {
            "1a. open (CNY)": "3812.15811325",
            "1b. open (USD)": "574.02199161",
            "2a. high (CNY)": "3905.36356006",
            "2b. high (USD)": "587.21125730",
            "3a. low (CNY)": "3719.18615984",
            "3b. low (USD)": "560.42933456",
            "4a. close (CNY)": "3875.76505428",
            "4b. close (USD)": "584.32118963",
            "5. volume": "2891621.76912000",
            "6. market cap (USD)": "1670252485.84999990"
        },
        "2016-08-14": {
            "1a. open (CNY)": "3906.54788950",
            "1b. open (USD)": "586.22335571",
            "2a. high (CNY)": "3987.73747130",
            "2b. high (USD)": "600.71667013",
            "3a. low (CNY)": "3762.90407409",
            "3b. low (USD)": "567.14178485",
            "4a. close (CNY)": "3813.59213696",
            "4b. close (USD)": "574.23792209",
            "5. volume": "4147120.54606000",
            "6. market cap (USD)": "2437967650.19000006"
        },
        "2016-08-07": {
            "1a. open (CNY)": "4136.63936166",
            "1b. open (USD)": "623.05522821",
            "2a. high (CNY)": "4170.35696804",
            "2b. high (USD)": "627.79842682",
            "3a. low (CNY)": "3302.55722947",
            "3b. low (USD)": "498.24169810",
            "4a. close (CNY)": "3917.35851469",
            "4b. close (USD)": "587.84561689",
            "5. volume": "6007548.30622000",
            "6. market cap (USD)": "3431414877.09999990"
        },
        "2016-07-31": {
            "1a. open (CNY)": "4425.52688804",
            "1b. open (USD)": "662.13370607",
            "2a. high (CNY)": "4431.71144477",
            "2b. high (USD)": "663.10664215",
            "3a. low (CNY)": "4129.51402133",
            "3b. low (USD)": "622.08602328",
            "4a. close (CNY)": "4137.22397058",
            "4b. close (USD)": "623.14328124",
            "5. volume": "3356797.09067000",
            "6. market cap (USD)": "2185182173.84999990"
        },
        "2016-07-24": {
            "1a. open (CNY)": "4543.27951090",
            "1b. open (USD)": "679.81445049",
            "2a. high (CNY)": "4543.27951090",
            "2b. high (USD)": "679.81445049",
            "3a. low (CNY)": "4335.97303399",
            "3b. low (USD)": "649.32570401",
            "4a. close (CNY)": "4381.00132143",
            "4b. close (USD)": "656.06883276",
            "5. volume": "3775195.99964000",
            "6. market cap (USD)": "2523739306.26999998"
        },
        "2016-07-17": {
            "1a. open (CNY)": "4339.82454331",
            "1b. open (USD)": "648.77983249",
            "2a. high (CNY)": "4571.37059678",
            "2b. high (USD)": "683.35311226",
            "3a. low (CNY)": "4329.54509335",
            "3b. low (USD)": "647.21408494",
            "4a. close (CNY)": "4541.55956576",
            "4b. close (USD)": "679.55709376",
            "5. volume": "4133233.76258000",
            "6. market cap (USD)": "2726663468.59999990"
        },
        "2016-07-10": {
            "1a. open (CNY)": "4387.93732478",
            "1b. open (USD)": "659.41579326",
            "2a. high (CNY)": "4599.88215786",
            "2b. high (USD)": "690.14433320",
            "3a. low (CNY)": "4088.77138709",
            "3b. low (USD)": "611.88972964",
            "4a. close (CNY)": "4343.87025528",
            "4b. close (USD)": "649.38464412",
            "5. volume": "4646584.12666000",
            "6. market cap (USD)": "3083209680.92000008"
        },
        "2016-07-03": {
            "1a. open (CNY)": "4139.95388375",
            "1b. open (USD)": "627.78708860",
            "2a. high (CNY)": "4736.31747774",
            "2b. high (USD)": "711.55318858",
            "3a. low (CNY)": "4069.15527952",
            "3b. low (USD)": "615.84641136",
            "4a. close (CNY)": "4389.10537765",
            "4b. close (USD)": "659.59132733",
            "5. volume": "4060744.86551000",
            "6. market cap (USD)": "2704370282.69000006"
        },
        "2016-06-26": {
            "1a. open (CNY)": "5092.94915031",
            "1b. open (USD)": "774.30450255",
            "2a. high (CNY)": "5095.13911246",
            "2b. high (USD)": "775.14420216",
            "3a. low (CNY)": "3563.22064670",
            "3b. low (USD)": "541.87775044",
            "4a. close (CNY)": "4124.77590688",
            "4b. close (USD)": "625.48548376",
            "5. volume": "4488079.17255000",
            "6. market cap (USD)": "2929435065.71999979"
        },
        "2016-06-19": {
            "1a. open (CNY)": "4679.50201697",
            "1b. open (USD)": "713.02699018",
            "2a. high (CNY)": "5155.45085808",
            "2b. high (USD)": "782.92754572",
            "3a. low (CNY)": "4482.15535306",
            "3b. low (USD)": "679.80537690",
            "4a. close (CNY)": "5102.53062828",
            "4b. close (USD)": "775.76121875",
            "5. volume": "3989337.33857000",
            "6. market cap (USD)": "2962705397.19000006"
        },
        "2016-06-12": {
            "1a. open (CNY)": "3813.84915710",
            "1b. open (USD)": "581.06163231",
            "2a. high (CNY)": "4762.69073712",
            "2b. high (USD)": "725.73306574",
            "3a. low (CNY)": "3775.34740735",
            "3b. low (USD)": "574.49597484",
            "4a. close (CNY)": "4691.78441578",
            "4b. close (USD)": "714.89848886",
            "5. volume": "3653681.43685000",
            "6. market cap (USD)": "2240582765.46000004"
        },
        "2016-06-05": {
            "1a. open (CNY)": "3722.86429059",
            "1b. open (USD)": "567.02489039",
            "2a. high (CNY)": "3883.89695952",
            "2b. high (USD)": "591.59906425",
            "3a. low (CNY)": "3498.97102732",
            "3b. low (USD)": "531.48404932",
            "4a. close (CNY)": "3811.91930485",
            "4b. close (USD)": "580.76760833",
            "5. volume": "3737261.02164000",
            "6. market cap (USD)": "2096719917.24000001"
        },
        "2016-05-29": {
            "1a. open (CNY)": "2917.91344828",
            "1b. open (USD)": "445.65395063",
            "2a. high (CNY)": "3951.88390564",
            "2b. high (USD)": "601.98727223",
            "3a. low (CNY)": "2912.96223821",
            "3b. low (USD)": "444.90522513",
            "4a. close (CNY)": "3717.44216061",
            "4b. close (USD)": "566.19905243",
            "5. volume": "2958907.71318000",
            "6. market cap (USD)": "1508178389.30999994"
        },
        "2016-05-22": {
            "1a. open (CNY)": "2989.53293795",
            "1b. open (USD)": "457.62250133",
            "2a. high (CNY)": "2998.62261707",
            "2b. high (USD)": "459.47951949",
            "3a. low (CNY)": "2883.74264656",
            "3b. low (USD)": "440.79507430",
            "4a. close (CNY)": "2918.45116803",
            "4b. close (USD)": "445.73607676",
            "5. volume": "2273001.40140000",
            "6. market cap (USD)": "1021942229.84000003"
        },
        "2016-05-15": {
            "1a. open (CNY)": "2961.77559599",
            "1b. open (USD)": "455.68316205",
            "2a. high (CNY)": "3006.53805121",
            "2b. high (USD)": "461.68224827",
            "3a. low (CNY)": "2928.06807459",
            "3b. low (USD)": "449.62484117",
            "4a. close (CNY)": "2988.28705039",
            "4b. close (USD)": "457.43178720",
            "5. volume": "2347106.88825000",
            "6. market cap (USD)": "1068901154.13000000"
        },
        "2016-05-08": {
            "1a. open (CNY)": "2921.25277058",
            "1b. open (USD)": "451.23977798",
            "2a. high (CNY)": "2982.23664683",
            "2b. high (USD)": "458.90758606",
            "3a. low (CNY)": "2859.38354395",
            "3b. low (USD)": "441.63794407",
            "4a. close (CNY)": "2969.00837649",
            "4b. close (USD)": "456.79595948",
            "5. volume": "2330083.66231000",
            "6. market cap (USD)": "1049903327.91999996"
        },
        "2016-05-01": {
            "1a. open (CNY)": "2971.14458382",
            "1b. open (USD)": "457.21938027",
            "2a. high (CNY)": "3026.81319410",
            "2b. high (USD)": "466.26325460",
            "3a. low (CNY)": "2834.52812566",
            "3b. low (USD)": "436.39209555",
            "4a. close (CNY)": "2918.68155690",
            "4b. close (USD)": "450.84260801",
            "5. volume": "2520335.57745000",
            "6. market cap (USD)": "1140824147.06999993"
        },
        "2016-04-24": {
            "1a. open (CNY)": "2775.48320839",
            "1b. open (USD)": "428.60567705",
            "2a. high (CNY)": "2978.82244756",
            "2b. high (USD)": "458.28242119",
            "3a. low (CNY)": "2775.48320839",
            "3b. low (USD)": "428.60567705",
            "4a. close (CNY)": "2971.90539902",
            "4b. close (USD)": "457.33645954",
            "5. volume": "2389696.34564000",
            "6. market cap (USD)": "1064331563.45000005"
        },
        "2016-04-17": {
            "1a. open (CNY)": "2727.99106415",
            "1b. open (USD)": "422.04385993",
            "2a. high (CNY)": "2813.17224145",
            "2b. high (USD)": "434.30812397",
            "3a. low (CNY)": "2714.77090926",
            "3b. low (USD)": "419.72287438",
            "4a. close (CNY)": "2776.97499376",
            "4b. close (USD)": "428.83604691",
            "5. volume": "2302829.88710000",
            "6. market cap (USD)": "983908272.49500000"
        },
        "2016-04-10": {
            "1a. open (CNY)": "2725.61403856",
            "1b. open (USD)": "420.54617931",
            "2a. high (CNY)": "2754.03945359",
            "2b. high (USD)": "425.21254682",
            "3a. low (CNY)": "2649.35654073",
            "3b. low (USD)": "409.74618344",
            "4a. close (CNY)": "2728.02808764",
            "4b. close (USD)": "422.04958778",
            "5. volume": "2269053.19611000",
            "6. market cap (USD)": "956338179.81400001"
        },
        "2016-04-03": {
            "1a. open (CNY)": "2794.81635229",
            "1b. open (USD)": "428.79289588",
            "2a. high (CNY)": "2806.67440858",
            "2b. high (USD)": "430.93750276",
            "3a. low (CNY)": "2657.44591722",
            "3b. low (USD)": "408.42752085",
            "4a. close (CNY)": "2726.28333402",
            "4b. close (USD)": "420.64944765",
            "5. volume": "2372035.27784000",
            "6. market cap (USD)": "993895150.54799998"
        },
        "2016-03-27": {
            "1a. open (CNY)": "2687.51911977",
            "1b. open (USD)": "415.34631828",
            "2a. high (CNY)": "2814.52142527",
            "2b. high (USD)": "432.13570067",
            "3a. low (CNY)": "2659.06778551",
            "3b. low (USD)": "411.01723562",
            "4a. close (CNY)": "2800.25242718",
            "4b. close (USD)": "429.62692217",
            "5. volume": "2429151.00371000",
            "6. market cap (USD)": "1021038504.70000005"
        },
        "2016-03-20": {
            "1a. open (CNY)": "2713.87047740",
            "1b. open (USD)": "418.06394764",
            "2a. high (CNY)": "2749.70456123",
            "2b. high (USD)": "423.71995529",
            "3a. low (CNY)": "2625.66585897",
            "3b. low (USD)": "405.69182023",
            "4a. close (CNY)": "2687.55937554",
            "4b. close (USD)": "415.35253967",
            "5. volume": "2477709.47495000",
            "6. market cap (USD)": "1033544664.80999994"
        },
        "2016-03-13": {
            "1a. open (CNY)": "2717.88762777",
            "1b. open (USD)": "417.05414221",
            "2a. high (CNY)": "2786.86742001",
            "2b. high (USD)": "428.68420146",
            "3a. low (CNY)": "2694.41904968",
            "3b. low (USD)": "413.85619730",
            "4a. close (CNY)": "2712.34961039",
            "4b. close (USD)": "417.82966245",
            "5. volume": "2570419.15770000",
            "6. market cap (USD)": "1080470576.25000000"
        },
        "2016-03-06": {
            "1a. open (CNY)": "2875.55889929",
            "1b. open (USD)": "439.74169612",
            "2a. high (CNY)": "2945.80445283",
            "2b. high (USD)": "449.76517109",
            "3a. low (CNY)": "2610.83565195",
            "3b. low (USD)": "400.47115490",
            "4a. close (CNY)": "2718.11620487",
            "4b. close (USD)": "417.08921689",
            "5. volume": "2891075.81000000",
            "6. market cap (USD)": "1233852944.68000007"
        },
        "2016-02-28": {
            "1a. open (CNY)": "2934.03262611",
            "1b. open (USD)": "449.79114625",
            "2a. high (CNY)": "2935.02262425",
            "2b. high (USD)": "449.94291430",
            "3a. low (CNY)": "2754.37771037",
            "3b. low (USD)": "421.75583630",
            "4a. close (CNY)": "2879.24920091",
            "4b. close (USD)": "440.30603146",
            "5. volume": "2606171.82506000",
            "6. market cap (USD)": "1136477880.22000003"
        },
        "2016-02-21": {
            "1a. open (CNY)": "2766.91416022",
            "1b. open (USD)": "421.87894584",
            "2a. high (CNY)": "2987.61114004",
            "2b. high (USD)": "458.07081397",
            "3a. low (CNY)": "2709.69359922",
            "3b. low (USD)": "416.44405382",
            "4a. close (CNY)": "2931.13938789",
            "4b. close (USD)": "449.34760894",
            "5. volume": "2616147.76443000",
            "6. market cap (USD)": "1132433396.15000010"
        },
        "2016-02-14": {
            "1a. open (CNY)": "2546.29603496",
            "1b. open (USD)": "387.17991006",
            "2a. high (CNY)": "2757.82447808",
            "2b. high (USD)": "420.49301722",
            "3a. low (CNY)": "2536.32559368",
            "3b. low (USD)": "385.79290017",
            "4a. close (CNY)": "2757.82447808",
            "4b. close (USD)": "420.49301722",
            "5. volume": "2262083.08466000",
            "6. market cap (USD)": "900431069.88999999"
        },
        "2016-02-07": {
            "1a. open (CNY)": "2472.17097994",
            "1b. open (USD)": "375.90719808",
            "2a. high (CNY)": "2609.99757175",
            "2b. high (USD)": "397.15294087",
            "3a. low (CNY)": "2469.18232623",
            "3b. low (USD)": "374.69734205",
            "4a. close (CNY)": "2546.45818665",
            "4b. close (USD)": "387.20456622",
            "5. volume": "2336982.59047000",
            "6. market cap (USD)": "902607679.44599998"
        },
        "2016-01-31": {
            "1a. open (CNY)": "2679.51499259",
            "1b. open (USD)": "407.23238737",
            "2a. high (CNY)": "2679.51499259",
            "2b. high (USD)": "407.23238737",
            "3a. low (CNY)": "2439.75264336",
            "3b. low (USD)": "371.02881260",
            "4a. close (CNY)": "2464.62690584",
            "4b. close (USD)": "374.76008012",
            "5. volume": "2504170.44428000",
            "6. market cap (USD)": "974883277.97300005"
        },
        "2016-01-24": {
            "1a. open (CNY)": "2534.09400365",
            "1b. open (USD)": "385.38505042",
            "2a. high (CNY)": "2843.29999117",
            "2b. high (USD)": "432.19771790",
            "3a. low (CNY)": "2502.88850669",
            "3b. low (USD)": "380.92178758",
            "4a. close (CNY)": "2676.56953974",
            "4b. close (USD)": "406.78473777",
            "5. volume": "2749829.97362000",
            "6. market cap (USD)": "1101800840.31999993"
        },
        "2016-01-17": {
            "1a. open (CNY)": "2935.31569602",
            "1b. open (USD)": "445.87909181",
            "2a. high (CNY)": "2960.80901203",
            "2b. high (USD)": "453.25216193",
            "3a. low (CNY)": "2361.65889748",
            "3b. low (USD)": "358.85506232",
            "4a. close (CNY)": "2537.07731062",
            "4b. close (USD)": "385.83875179",
            "5. volume": "2621925.00084000",
            "6. market cap (USD)": "1075060375.25000000"
        },
        "2016-01-10": {
            "1a. open (CNY)": "2815.75385905",
            "1b. open (USD)": "433.02795105",
            "2a. high (CNY)": "3057.89958615",
            "2b. high (USD)": "463.88201690",
            "3a. low (CNY)": "2782.06644131",
            "3b. low (USD)": "425.32433131",
            "4a. close (CNY)": "2935.74959471",
            "4b. close (USD)": "445.94500171",
            "5. volume": "2326941.05923000",
            "6. market cap (USD)": "1036155993.82000005"
        },
        "2016-01-03": {
            "1a. open (CNY)": "2717.20182176",
            "1b. open (USD)": "420.09338487",
            "2a. high (CNY)": "2871.77292801",
            "2b. high (USD)": "441.76833418",
            "3a. low (CNY)": "2716.59624725",
            "3b. low (USD)": "419.73595249",
            "4a. close (CNY)": "2814.12497076",
            "4b. close (USD)": "432.77744828",
            "5. volume": "2651037.54763000",
            "6. market cap (USD)": "1149983558.75999999"
        },
        "2015-12-27": {
            "1a. open (CNY)": "2957.87039675",
            "1b. open (USD)": "456.29565131",
            "2a. high (CNY)": "3027.44305999",
            "2b. high (USD)": "467.63195779",
            "3a. low (CNY)": "2588.11549229",
            "3b. low (USD)": "400.11141590",
            "4a. close (CNY)": "2715.28925026",
            "4b. close (USD)": "419.79769148",
            "5. volume": "3036297.44123000",
            "6. market cap (USD)": "1347736932.66000009"
        },
        "2015-12-20": {
            "1a. open (CNY)": "2890.91189053",
            "1b. open (USD)": "447.99231657",
            "2a. high (CNY)": "3094.90937219",
            "2b. high (USD)": "478.48677060",
            "3a. low (CNY)": "2861.76957896",
            "3b. low (USD)": "443.28528711",
            "4a. close (CNY)": "2955.82892406",
            "4b. close (USD)": "455.98072368",
            "5. volume": "3057694.00938000",
            "6. market cap (USD)": "1430810308.60999990"
        },
        "2015-12-13": {
            "1a. open (CNY)": "2576.63883117",
            "1b. open (USD)": "402.40113181",
            "2a. high (CNY)": "3124.26894891",
            "2b. high (USD)": "484.01913057",
            "3a. low (CNY)": "2549.21584834",
            "3b. low (USD)": "398.18929781",
            "4a. close (CNY)": "2886.21719325",
            "4b. close (USD)": "447.26479931",
            "5. volume": "2842767.14017000",
            "6. market cap (USD)": "1240264087.01999998"
        },
        "2015-12-06": {
            "1a. open (CNY)": "2378.58113863",
            "1b. open (USD)": "371.99798229",
            "2a. high (CNY)": "2641.38458180",
            "2b. high (USD)": "412.66346840",
            "3a. low (CNY)": "2242.40691723",
            "3b. low (USD)": "350.44868940",
            "4a. close (CNY)": "2587.70577366",
            "4b. close (USD)": "404.12948820",
            "5. volume": "1994097.07016000",
            "6. market cap (USD)": "758039973.96599996"
        },
        "2015-11-29": {
            "1a. open (CNY)": "2082.09702501",
            "1b. open (USD)": "326.05466016",
            "2a. high (CNY)": "2383.80071158",
            "2b. high (USD)": "372.80613423",
            "3a. low (CNY)": "2037.37382830",
            "3b. low (USD)": "318.85560890",
            "4a. close (CNY)": "2379.01957749",
            "4b. close (USD)": "372.06655190",
            "5. volume": "1564554.69283000",
            "6. market cap (USD)": "547676737.28100002"
        },
        "2015-11-22": {
            "1a. open (CNY)": "2060.04879431",
            "1b. open (USD)": "323.08257298",
            "2a. high (CNY)": "2146.76858710",
            "2b. high (USD)": "336.83678006",
            "3a. low (CNY)": "2017.57083158",
            "3b. low (USD)": "316.17826713",
            "4a. close (CNY)": "2083.97876432",
            "4b. close (USD)": "326.34933897",
            "5. volume": "1358277.85290000",
            "6. market cap (USD)": "447383101.59200001"
        },
        "2015-11-15": {
            "1a. open (CNY)": "2467.03483251",
            "1b. open (USD)": "388.29417906",
            "2a. high (CNY)": "2547.88419434",
            "2b. high (USD)": "400.59875481",
            "3a. low (CNY)": "1875.62192028",
            "3b. low (USD)": "294.87739373",
            "4a. close (CNY)": "2053.10937631",
            "4b. close (USD)": "321.99424681",
            "5. volume": "1704871.60882000",
            "6. market cap (USD)": "576976575.27999997"
        },
        "2015-11-08": {
            "1a. open (CNY)": "2219.05371002",
            "1b. open (USD)": "351.26282340",
            "2a. high (CNY)": "3318.99064347",
            "2b. high (USD)": "523.81653956",
            "3a. low (CNY)": "2213.50665717",
            "3b. low (USD)": "350.54290153",
            "4a. close (CNY)": "2472.61238929",
            "4b. close (USD)": "389.17204782",
            "5. volume": "1868788.41484000",
            "6. market cap (USD)": "770965058.61399996"
        },
        "2015-11-01": {
            "1a. open (CNY)": "1869.07541719",
            "1b. open (USD)": "294.37642708",
            "2a. high (CNY)": "2287.93813014",
            "2b. high (USD)": "360.34437288",
            "3a. low (CNY)": "1847.65066789",
            "3b. low (USD)": "290.86920972",
            "4a. close (CNY)": "2219.51799992",
            "4b. close (USD)": "351.33631769",
            "5. volume": "7885329.04055000",
            "6. market cap (USD)": "2573114117.63000011"
        },
        "2015-10-25": {
            "1a. open (CNY)": "1726.89108587",
            "1b. open (USD)": "271.86444111",
            "2a. high (CNY)": "1934.19138838",
            "2b. high (USD)": "304.63400891",
            "3a. low (CNY)": "1714.96799800",
            "3b. low (USD)": "270.16942980",
            "4a. close (CNY)": "1873.45989259",
            "4b. close (USD)": "295.06697504",
            "5. volume": "6152407.61328000",
            "6. market cap (USD)": "1730778422.75999999"
        },
        "2015-10-18": {
            "1a. open (CNY)": "1586.14785690",
            "1b. open (USD)": "249.94962974",
            "2a. high (CNY)": "1822.60092007",
            "2b. high (USD)": "286.90403533",
            "3a. low (CNY)": "1572.20101380",
            "3b. low (USD)": "248.42228532",
            "4a. close (CNY)": "1724.78255057",
            "4b. close (USD)": "271.53249443",
            "5. volume": "6121641.46384000",
            "6. market cap (USD)": "1623818442.32999992"
        },
        "2015-10-11": {
            "1a. open (CNY)": "1540.83719731",
            "1b. open (USD)": "242.42589925",
            "2a. high (CNY)": "1600.40512786",
            "2b. high (USD)": "251.78210752",
            "3a. low (CNY)": "1539.80617013",
            "3b. low (USD)": "242.27816880",
            "4a. close (CNY)": "1587.15363751",
            "4b. close (USD)": "250.10812347",
            "5. volume": "3368373.29664000",
            "6. market cap (USD)": "835440137.81400001"
        },
        "2015-10-04": {
            "1a. open (CNY)": "1510.71634920",
            "1b. open (USD)": "236.99816283",
            "2a. high (CNY)": "1570.75666831",
            "2b. high (USD)": "246.60021531",
            "3a. low (CNY)": "1509.55601114",
            "3b. low (USD)": "236.78492838",
            "4a. close (CNY)": "1540.81663135",
            "4b. close (USD)": "242.42266353",
            "5. volume": "3357885.25538000",
            "6. market cap (USD)": "815583349.84899998"
        },
        "2015-09-27": {
            "1a. open (CNY)": "1485.06654813",
            "1b. open (USD)": "233.29634505",
            "2a. high (CNY)": "1532.11406727",
            "2b. high (USD)": "240.25955937",
            "3a. low (CNY)": "1449.84494812",
            "3b. low (USD)": "227.51338128",
            "4a. close (CNY)": "1509.58932454",
            "4b. close (USD)": "236.82135746",
            "5. volume": "2812581.77538000",
            "6. market cap (USD)": "663426750.63000000"
        },
        "2015-09-20": {
            "1a. open (CNY)": "1480.30531089",
            "1b. open (USD)": "232.20694013",
            "2a. high (CNY)": "1504.85949387",
            "2b. high (USD)": "236.37088497",
            "3a. low (CNY)": "1463.90246887",
            "3b. low (USD)": "229.74203600",
            "4a. close (CNY)": "1484.96655179",
            "4b. close (USD)": "233.28063614",
            "5. volume": "1856056.75040000",
            "6. market cap (USD)": "433335879.81500000"
        },
        "2015-09-13": {
            "1a. open (CNY)": "1531.34868717",
            "1b. open (USD)": "240.92621205",
            "2a. high (CNY)": "1568.25527466",
            "2b. high (USD)": "246.39482722",
            "3a. low (CNY)": "1471.22072215",
            "3b. low (USD)": "230.78189319",
            "4a. close (CNY)": "1480.42458919",
            "4b. close (USD)": "232.22565062",
            "5. volume": "1739863.04957000",
            "6. market cap (USD)": "416608809.43500000"
        },
        "2015-09-06": {
            "1a. open (CNY)": "1460.17263921",
            "1b. open (USD)": "228.54049372",
            "2a. high (CNY)": "1549.84180880",
            "2b. high (USD)": "243.80273697",
            "3a. low (CNY)": "1437.52872325",
            "3b. low (USD)": "225.26996177",
            "4a. close (CNY)": "1533.44956651",
            "4b. close (USD)": "241.25674220",
            "5. volume": "1945141.92138000",
            "6. market cap (USD)": "451605368.97200000"
        },
        "2015-08-30": {
            "1a. open (CNY)": "1457.60216651",
            "1b. open (USD)": "228.19460489",
            "2a. high (CNY)": "1500.29304744",
            "2b. high (USD)": "235.40942063",
            "3a. low (CNY)": "1295.22820726",
            "3b. low (USD)": "202.33388226",
            "4a. close (CNY)": "1455.55645065",
            "4b. close (USD)": "227.81798599",
            "5. volume": "3295416.66574000",
            "6. market cap (USD)": "736320998.51100004"
        },
        "2015-08-23": {
            "1a. open (CNY)": "1647.19650757",
            "1b. open (USD)": "257.73084775",
            "2a. high (CNY)": "1657.83645964",
            "2b. high (USD)": "259.10779661",
            "3a. low (CNY)": "1427.29585615",
            "3b. low (USD)": "223.42020592",
            "4a. close (CNY)": "1458.51640494",
            "4b. close (USD)": "228.33773330",
            "5. volume": "2618030.83594000",
            "6. market cap (USD)": "613319526.05900002"
        },
        "2015-08-16": {
            "1a. open (CNY)": "1631.24490872",
            "1b. open (USD)": "262.73830277",
            "2a. high (CNY)": "1704.54275046",
            "2b. high (USD)": "268.28562695",
            "3a. low (CNY)": "1618.56997022",
            "3b. low (USD)": "256.23829087",
            "4a. close (CNY)": "1647.53652987",
            "4b. close (USD)": "257.78404980",
            "5. volume": "1902434.87785000",
            "6. market cap (USD)": "500165113.76300001"
        },
        "2015-08-09": {
            "1a. open (CNY)": "1739.70345935",
            "1b. open (USD)": "280.16082352",
            "2a. high (CNY)": "1770.86181334",
            "2b. high (USD)": "285.14686183",
            "3a. low (CNY)": "1607.04609887",
            "3b. low (USD)": "258.80734606",
            "4a. close (CNY)": "1630.81729289",
            "4b. close (USD)": "262.66942834",
            "5. volume": "1727893.06134000",
            "6. market cap (USD)": "472742926.44000000"
        },
        "2015-08-02": {
            "1a. open (CNY)": "1807.99465285",
            "1b. open (USD)": "292.19445030",
            "2a. high (CNY)": "1841.85828307",
            "2b. high (USD)": "297.59845791",
            "3a. low (CNY)": "1704.04951258",
            "3b. low (USD)": "274.44299878",
            "4a. close (CNY)": "1738.58468745",
            "4b. close (USD)": "279.98065715",
            "5. volume": "1661238.55030000",
            "6. market cap (USD)": "476243914.49100000"
        },
        "2015-07-26": {
            "1a. open (CNY)": "1680.29857606",
            "1b. open (USD)": "271.55322436",
            "2a. high (CNY)": "1814.73229879",
            "2b. high (USD)": "293.28144187",
            "3a. low (CNY)": "1674.44840447",
            "3b. low (USD)": "270.61608705",
            "4a. close (CNY)": "1808.76363573",
            "4b. close (USD)": "292.31872751",
            "5. volume": "1474872.43516000",
            "6. market cap (USD)": "417055105.80299997"
        },
        "2015-07-19": {
            "1a. open (CNY)": "1972.35543981",
            "1b. open (USD)": "318.45529865",
            "2a. high (CNY)": "1972.35543981",
            "2b. high (USD)": "318.45529865",
            "3a. low (CNY)": "1671.27040244",
            "3b. low (USD)": "270.06598538",
            "4a. close (CNY)": "1682.30163567",
            "4b. close (USD)": "271.87693903",
            "5. volume": "1850973.69213000",
            "6. market cap (USD)": "523196069.79299998"
        },
        "2015-07-12": {
            "1a. open (CNY)": "1689.50687111",
            "1b. open (USD)": "272.62308509",
            "2a. high (CNY)": "2015.37706517",
            "2b. high (USD)": "325.55355803",
            "3a. low (CNY)": "1643.89872168",
            "3b. low (USD)": "265.57535853",
            "4a. close (CNY)": "1972.72456893",
            "4b. close (USD)": "318.51489801",
            "5. volume": "2480798.93936000",
            "6. market cap (USD)": "712428043.15900004"
        },
        "2015-07-05": {
            "1a. open (CNY)": "1545.84100002",
            "1b. open (USD)": "248.89154587",
            "2a. high (CNY)": "1698.12131207",
            "2b. high (USD)": "274.51989320",
            "3a. low (CNY)": "1544.46456051",
            "3b. low (USD)": "247.94655734",
            "4a. close (CNY)": "1689.94940453",
            "4b. close (USD)": "272.69449340",
            "5. volume": "2056836.77833000",
            "6. market cap (USD)": "538318016.00899994"
        },
        "2015-06-28": {
            "1a. open (CNY)": "1515.41674186",
            "1b. open (USD)": "244.94338949",
            "2a. high (CNY)": "1568.89140642",
            "2b. high (USD)": "253.49151066",
            "3a. low (CNY)": "1489.00047210",
            "3b. low (USD)": "240.63915162",
            "4a. close (CNY)": "1546.01014323",
            "4b. close (USD)": "248.91877915",
            "5. volume": "1460513.13236000",
            "6. market cap (USD)": "360090315.70400000"
        },
        "2015-06-21": {
            "1a. open (CNY)": "1453.49428240",
            "1b. open (USD)": "234.64490949",
            "2a. high (CNY)": "1635.24178928",
            "2b. high (USD)": "264.15334157",
            "3a. low (CNY)": "1451.81384081",
            "3b. low (USD)": "234.20122155",
            "4a. close (CNY)": "1516.64430642",
            "4b. close (USD)": "245.14180608",
            "5. volume": "1999040.43802000",
            "6. market cap (USD)": "500273544.42699999"
        },
        "2015-06-14": {
            "1a. open (CNY)": "1380.28201505",
            "1b. open (USD)": "223.16576067",
            "2a. high (CNY)": "1462.62701256",
            "2b. high (USD)": "236.30465071",
            "3a. low (CNY)": "1379.34216711",
            "3b. low (USD)": "222.96657998",
            "4a. close (CNY)": "1453.69629562",
            "4b. close (USD)": "234.67752150",
            "5. volume": "1180282.09132000",
            "6. market cap (USD)": "272422376.43099999"
        },
        "2015-06-07": {
            "1a. open (CNY)": "1435.75273619",
            "1b. open (USD)": "232.28576461",
            "2a. high (CNY)": "1443.63551010",
            "2b. high (USD)": "233.64160720",
            "3a. low (CNY)": "1373.73973067",
            "3b. low (USD)": "222.11661467",
            "4a. close (CNY)": "1380.13874120",
            "4b. close (USD)": "223.14259597",
            "5. volume": "1125860.16062000",
            "6. market cap (USD)": "254412989.14600000"
        },
        "2015-05-31": {
            "1a. open (CNY)": "1503.93985162",
            "1b. open (USD)": "243.42221485",
            "2a. high (CNY)": "1503.93985162",
            "2b. high (USD)": "243.42221485",
            "3a. low (CNY)": "1433.22118974",
            "3b. low (USD)": "231.87619394",
            "4a. close (CNY)": "1435.16679185",
            "4b. close (USD)": "232.19096658",
            "5. volume": "1287492.95829000",
            "6. market cap (USD)": "306437344.23100001"
        },
        "2015-05-24": {
            "1a. open (CNY)": "1467.26314300",
            "1b. open (USD)": "237.30034329",
            "2a. high (CNY)": "1509.31990606",
            "2b. high (USD)": "244.30882800",
            "3a. low (CNY)": "1444.55625553",
            "3b. low (USD)": "233.51630380",
            "4a. close (CNY)": "1504.33299049",
            "4b. close (USD)": "243.48584687",
            "5. volume": "1573970.06261000",
            "6. market cap (USD)": "375385052.86500001"
        },
        "2015-05-17": {
            "1a. open (CNY)": "1490.16503366",
            "1b. open (USD)": "240.89252819",
            "2a. high (CNY)": "1515.91978547",
            "2b. high (USD)": "245.13548260",
            "3a. low (CNY)": "1443.19067832",
            "3b. low (USD)": "233.51421066",
            "4a. close (CNY)": "1466.70402820",
            "4b. close (USD)": "237.20991770",
            "5. volume": "2233917.18632000",
            "6. market cap (USD)": "534123285.98900002"
        },
        "2015-05-10": {
            "1a. open (CNY)": "1487.93981009",
            "1b. open (USD)": "240.49043448",
            "2a. high (CNY)": "1538.17934009",
            "2b. high (USD)": "248.58769041",
            "3a. low (CNY)": "1414.61201604",
            "3b. low (USD)": "228.75071476",
            "4a. close (CNY)": "1491.15278376",
            "4b. close (USD)": "241.05220287",
            "5. volume": "2965323.15727000",
            "6. market cap (USD)": "708236320.95799994"
        },
        "2015-05-03": {
            "1a. open (CNY)": "1353.93619820",
            "1b. open (USD)": "219.20895163",
            "2a. high (CNY)": "1506.38992114",
            "2b. high (USD)": "243.47088644",
            "3a. low (CNY)": "1348.81328146",
            "3b. low (USD)": "217.67326890",
            "4a. close (CNY)": "1488.88280628",
            "4b. close (USD)": "240.64284761",
            "5. volume": "3045032.43272000",
            "6. market cap (USD)": "705700286.87600005"
        },
        "2015-04-26": {
            "1a. open (CNY)": "1374.70325894",
            "1b. open (USD)": "222.51561651",
            "2a. high (CNY)": "1478.01498331",
            "2b. high (USD)": "239.27932377",
            "3a. low (CNY)": "1328.43480655",
            "3b. low (USD)": "215.08920472",
            "4a. close (CNY)": "1353.40893503",
            "4b. close (USD)": "219.12358512",
            "5. volume": "2953384.04034000",
            "6. market cap (USD)": "679440087.25199997"
        },
        "2015-04-19": {
            "1a. open (CNY)": "1460.98718442",
            "1b. open (USD)": "236.07480654",
            "2a. high (CNY)": "1471.51534010",
            "2b. high (USD)": "237.59633169",
            "3a. low (CNY)": "1301.86205073",
            "3b. low (USD)": "210.73196662",
            "4a. close (CNY)": "1375.77658073",
            "4b. close (USD)": "222.68934918",
            "5. volume": "3589613.43112000",
            "6. market cap (USD)": "803496263.97899997"
        },
        "2015-04-12": {
            "1a. open (CNY)": "1612.85880922",
            "1b. open (USD)": "261.94075450",
            "2a. high (CNY)": "1618.09798779",
            "2b. high (USD)": "262.89982009",
            "3a. low (CNY)": "1437.62248757",
            "3b. low (USD)": "232.27883487",
            "4a. close (CNY)": "1461.17276637",
            "4b. close (USD)": "236.10479396",
            "5. volume": "3131116.22080000",
            "6. market cap (USD)": "762922787.89400005"
        },
        "2015-04-05": {
            "1a. open (CNY)": "1508.06278138",
            "1b. open (USD)": "243.43264176",
            "2a. high (CNY)": "1615.10816725",
            "2b. high (USD)": "262.30947575",
            "3a. low (CNY)": "1475.29560471",
            "3b. low (USD)": "237.87877300",
            "4a. close (CNY)": "1612.83919287",
            "4b. close (USD)": "261.93756866",
            "5. volume": "3044113.11020000",
            "6. market cap (USD)": "768269944.62699997"
        },
        "2015-03-29": {
            "1a. open (CNY)": "1656.96909651",
            "1b. open (USD)": "267.63389722",
            "2a. high (CNY)": "1671.41187763",
            "2b. high (USD)": "269.69574612",
            "3a. low (CNY)": "1449.22095126",
            "3b. low (USD)": "234.04821841",
            "4a. close (CNY)": "1505.42382310",
            "4b. close (USD)": "243.00665911",
            "5. volume": "3533195.42075000",
            "6. market cap (USD)": "881607725.24500000"
        },
        "2015-03-22": {
            "1a. open (CNY)": "1787.07370003",
            "1b. open (USD)": "286.44152042",
            "2a. high (CNY)": "1839.04415827",
            "2b. high (USD)": "294.62805475",
            "3a. low (CNY)": "1542.64907710",
            "3b. low (USD)": "248.40601983",
            "4a. close (CNY)": "1656.94492504",
            "4b. close (USD)": "267.62999304",
            "5. volume": "3363741.71768000",
            "6. market cap (USD)": "899946514.02300000"
        },
        "2015-03-15": {
            "1a. open (CNY)": "1710.18756350",
            "1b. open (USD)": "273.96323712",
            "2a. high (CNY)": "1878.94092358",
            "2b. high (USD)": "301.02018831",
            "3a. low (CNY)": "1703.75627332",
            "3b. low (USD)": "272.93297757",
            "4a. close (CNY)": "1786.87494500",
            "4b. close (USD)": "286.40966292",
            "5. volume": "3435446.53453000",
            "6. market cap (USD)": "997584002.60099995"
        },
        "2015-03-08": {
            "1a. open (CNY)": "1629.51762849",
            "1b. open (USD)": "260.83650354",
            "2a. high (CNY)": "1791.99029962",
            "2b. high (USD)": "286.58872642",
            "3a. low (CNY)": "1617.77375106",
            "3b. low (USD)": "258.77813263",
            "4a. close (CNY)": "1709.89586289",
            "4b. close (USD)": "273.91650819",
            "5. volume": "3421022.28006000",
            "6. market cap (USD)": "942358335.96000004"
        },
        "2015-03-01": {
            "1a. open (CNY)": "1470.50216111",
            "1b. open (USD)": "235.88837164",
            "2a. high (CNY)": "1637.55670537",
            "2b. high (USD)": "262.12331669",
            "3a. low (CNY)": "1455.06984088",
            "3b. low (USD)": "233.40345916",
            "4a. close (CNY)": "1629.94857602",
            "4b. close (USD)": "260.90548521",
            "5. volume": "2401335.84292000",
            "6. market cap (USD)": "595458028.07099998"
        },
        "2015-02-22": {
            "1a. open (CNY)": "1460.89210065",
            "1b. open (USD)": "234.86814912",
            "2a. high (CNY)": "1541.37466575",
            "2b. high (USD)": "247.25124819",
            "3a. low (CNY)": "1425.63476613",
            "3b. low (USD)": "229.26358045",
            "4a. close (CNY)": "1470.11078037",
            "4b. close (USD)": "235.82558890",
            "5. volume": "2830328.74944000",
            "6. market cap (USD)": "676639322.97000003"
        },
        "2015-02-15": {
            "1a. open (CNY)": "1386.42421578",
            "1b. open (USD)": "222.71116482",
            "2a. high (CNY)": "1660.74753063",
            "2b. high (USD)": "266.99897857",
            "3a. low (CNY)": "1340.76321335",
            "3b. low (USD)": "215.47232987",
            "4a. close (CNY)": "1458.61209320",
            "4b. close (USD)": "234.50159150",
            "5. volume": "3286446.12256000",
            "6. market cap (USD)": "766572237.89100003"
        },
        "2015-02-08": {
            "1a. open (CNY)": "1415.71546724",
            "1b. open (USD)": "227.04652651",
            "2a. high (CNY)": "1543.81798586",
            "2b. high (USD)": "247.42457162",
            "3a. low (CNY)": "1338.32062229",
            "3b. low (USD)": "214.72545348",
            "4a. close (CNY)": "1385.36552507",
            "4b. close (USD)": "222.54109982",
            "5. volume": "3050472.71042000",
            "6. market cap (USD)": "690459303.47800004"
        },
        "2015-02-01": {
            "1a. open (CNY)": "1549.41423875",
            "1b. open (USD)": "249.32106555",
            "2a. high (CNY)": "1907.16514422",
            "2b. high (USD)": "305.84845539",
            "3a. low (CNY)": "1310.96611791",
            "3b. low (USD)": "210.37922002",
            "4a. close (CNY)": "1416.86814706",
            "4b. close (USD)": "227.23138848",
            "5. volume": "4634434.09350000",
            "6. market cap (USD)": "1135787888.90000010"
        },
        "2015-01-25": {
            "1a. open (CNY)": "1297.89350653",
            "1b. open (USD)": "209.58152058",
            "2a. high (CNY)": "1569.24297940",
            "2b. high (USD)": "252.51176989",
            "3a. low (CNY)": "1260.34696439",
            "3b. low (USD)": "203.32958370",
            "4a. close (CNY)": "1548.98648382",
            "4b. close (USD)": "249.25223417",
            "5. volume": "3812492.25714000",
            "6. market cap (USD)": "874848339.17799997"
        },
        "2015-01-18": {
            "1a. open (CNY)": "1638.74113365",
            "1b. open (USD)": "264.67842768",
            "2a. high (CNY)": "1681.92926619",
            "2b. high (USD)": "271.86377180",
            "3a. low (CNY)": "978.70439490",
            "3b. low (USD)": "158.34544795",
            "4a. close (CNY)": "1292.04238600",
            "4b. close (USD)": "208.63669211",
            "5. volume": "5220783.73562000",
            "6. market cap (USD)": "1072899162.61000001"
        },
        "2015-01-11": {
            "1a. open (CNY)": "1622.98462877",
            "1b. open (USD)": "262.01995710",
            "2a. high (CNY)": "1801.94429081",
            "2b. high (USD)": "290.70303764",
            "3a. low (CNY)": "1617.97200742",
            "3b. low (USD)": "261.32393834",
            "4a. close (CNY)": "1637.06833420",
            "4b. close (USD)": "264.40824838",
            "5. volume": "2842299.64235000",
            "6. market cap (USD)": "787804428.54400003"
        },
        "2015-01-04": {
            "1a. open (CNY)": "1971.47043710",
            "1b. open (USD)": "317.87256418",
            "2a. high (CNY)": "1987.71049136",
            "2b. high (USD)": "320.49105015",
            "3a. low (CNY)": "1584.11991855",
            "3b. low (USD)": "255.74551092",
            "4a. close (CNY)": "1618.87476121",
            "4b. close (USD)": "261.35644661",
            "5. volume": "2557169.90585000",
            "6. market cap (USD)": "749151073.59200001"
        },
        "2014-12-28": {
            "1a. open (CNY)": "1998.22605118",
            "1b. open (USD)": "322.04748280",
            "2a. high (CNY)": "2105.35746796",
            "2b. high (USD)": "339.08812346",
            "3a. low (CNY)": "1927.02489920",
            "3b. low (USD)": "310.70633088",
            "4a. close (CNY)": "1968.12484699",
            "4b. close (USD)": "317.33313367",
            "5. volume": "2540501.37497000",
            "6. market cap (USD)": "826145257.30200005"
        },
        "2014-12-21": {
            "1a. open (CNY)": "2173.81840984",
            "1b. open (USD)": "352.11611437",
            "2a. high (CNY)": "2174.94638770",
            "2b. high (USD)": "352.29882475",
            "3a. low (CNY)": "1884.64757285",
            "3b. low (USD)": "304.07399380",
            "4a. close (CNY)": "1997.16917275",
            "4b. close (USD)": "321.87714920",
            "5. volume": "2987998.02599000",
            "6. market cap (USD)": "964275174.83599997"
        },
        "2014-12-14": {
            "1a. open (CNY)": "2308.06975938",
            "1b. open (USD)": "375.34423285",
            "2a. high (CNY)": "2315.36601593",
            "2b. high (USD)": "376.53076883",
            "3a. low (CNY)": "2084.51905665",
            "3b. low (USD)": "338.07313482",
            "4a. close (CNY)": "2174.44938909",
            "4b. close (USD)": "352.21832069",
            "5. volume": "2960573.53496000",
            "6. market cap (USD)": "1041017060.23000002"
        },
        "2014-12-07": {
            "1a. open (CNY)": "2319.44592915",
            "1b. open (USD)": "377.64761313",
            "2a. high (CNY)": "2375.28727063",
            "2b. high (USD)": "386.41595300",
            "3a. low (CNY)": "2265.97221044",
            "3b. low (USD)": "368.43279359",
            "4a. close (CNY)": "2307.67637873",
            "4b. close (USD)": "375.28026028",
            "5. volume": "2579498.49024000",
            "6. market cap (USD)": "975143789.10899997"
        },
        "2014-11-30": {
            "1a. open (CNY)": "2241.88790713",
            "1b. open (USD)": "365.82864120",
            "2a. high (CNY)": "2447.44257543",
            "2b. high (USD)": "398.50178950",
            "3a. low (CNY)": "2201.29843181",
            "3b. low (USD)": "358.39362302",
            "4a. close (CNY)": "2316.42823287",
            "4b. close (USD)": "377.15627777",
            "5. volume": "4019869.67139000",
            "6. market cap (USD)": "1507011449.81999993"
        },
        "2014-11-23": {
            "1a. open (CNY)": "2365.89941300",
            "1b. open (USD)": "385.82847108",
            "2a. high (CNY)": "2509.35487207",
            "2b. high (USD)": "409.41666654",
            "3a. low (CNY)": "2103.13776354",
            "3b. low (USD)": "343.29460657",
            "4a. close (CNY)": "2242.83082268",
            "4b. close (USD)": "365.98250506",
            "5. volume": "3930436.22006000",
            "6. market cap (USD)": "1449945901.02999997"
        },
        "2014-11-16": {
            "1a. open (CNY)": "2208.44680135",
            "1b. open (USD)": "360.39340231",
            "2a. high (CNY)": "2951.51867796",
            "2b. high (USD)": "481.40736722",
            "3a. low (CNY)": "2180.95433561",
            "3b. low (USD)": "355.92778937",
            "4a. close (CNY)": "2360.13453038",
            "4b. close (USD)": "384.88833988",
            "5. volume": "6299288.06855000",
            "6. market cap (USD)": "2547634971.00000000"
        },
        "2014-11-09": {
            "1a. open (CNY)": "1971.98986400",
            "1b. open (USD)": "321.57866977",
            "2a. high (CNY)": "2212.55546389",
            "2b. high (USD)": "361.06388931",
            "3a. low (CNY)": "1959.35875392",
            "3b. low (USD)": "320.04767558",
            "4a. close (CNY)": "2211.50116373",
            "4b. close (USD)": "360.89183951",
            "5. volume": "3046216.68729000",
            "6. market cap (USD)": "1034820803.15999997"
        },
        "2014-11-02": {
            "1a. open (CNY)": "2149.59542893",
            "1b. open (USD)": "350.78323080",
            "2a. high (CNY)": "2178.99890461",
            "2b. high (USD)": "356.00089803",
            "3a. low (CNY)": "1958.27606541",
            "3b. low (USD)": "320.04585022",
            "4a. close (CNY)": "1974.55360052",
            "4b. close (USD)": "321.99674645",
            "5. volume": "2370947.46337000",
            "6. market cap (USD)": "801808154.72300005"
        },
        "2014-10-26": {
            "1a. open (CNY)": "2369.96672661",
            "1b. open (USD)": "386.70113304",
            "2a. high (CNY)": "2385.31759701",
            "2b. high (USD)": "389.40247934",
            "3a. low (CNY)": "2100.74538058",
            "3b. low (USD)": "343.15761576",
            "4a. close (CNY)": "2147.49526899",
            "4b. close (USD)": "350.44051473",
            "5. volume": "2229509.05825000",
            "6. market cap (USD)": "809474707.45299995"
        },
        "2014-10-19": {
            "1a. open (CNY)": "2284.55456088",
            "1b. open (USD)": "372.57012629",
            "2a. high (CNY)": "2494.49064432",
            "2b. high (USD)": "407.10877823",
            "3a. low (CNY)": "2250.56613643",
            "3b. low (USD)": "367.13678856",
            "4a. close (CNY)": "2365.87059789",
            "4b. close (USD)": "386.03277867",
            "5. volume": "2795793.54668000",
            "6. market cap (USD)": "1087043637.42000008"
        },
        "2014-10-12": {
            "1a. open (CNY)": "1978.05367727",
            "1b. open (USD)": "322.11503612",
            "2a. high (CNY)": "2331.47167652",
            "2b. high (USD)": "380.20274625",
            "3a. low (CNY)": "1869.16190829",
            "3b. low (USD)": "304.25974081",
            "4a. close (CNY)": "2293.12292589",
            "4b. close (USD)": "373.96747390",
            "5. volume": "3213744.68542000",
            "6. market cap (USD)": "1138191229.70000005"
        },
        "2014-10-05": {
            "1a. open (CNY)": "2311.99449566",
            "1b. open (USD)": "377.09059813",
            "2a. high (CNY)": "2420.72946046",
            "2b. high (USD)": "394.15129717",
            "3a. low (CNY)": "1833.21867834",
            "3b. low (USD)": "298.56738599",
            "4a. close (CNY)": "1972.36781918",
            "4b. close (USD)": "321.18912577",
            "5. volume": "1878863.29496000",
            "6. market cap (USD)": "664283565.74600005"
        },
        "2014-09-28": {
            "1a. open (CNY)": "2452.22148587",
            "1b. open (USD)": "399.21165845",
            "2a. high (CNY)": "2694.64176886",
            "2b. high (USD)": "438.80606230",
            "3a. low (CNY)": "2290.22771618",
            "3b. low (USD)": "373.51115418",
            "4a. close (CNY)": "2313.64169009",
            "4b. close (USD)": "377.35925861",
            "5. volume": "1399118.48280000",
            "6. market cap (USD)": "573416119.34300005"
        },
        "2014-09-21": {
            "1a. open (CNY)": "2924.17049870",
            "1b. open (USD)": "476.47865955",
            "2a. high (CNY)": "2924.17049870",
            "2b. high (USD)": "476.47865955",
            "3a. low (CNY)": "2366.68217518",
            "3b. low (USD)": "385.24117760",
            "4a. close (CNY)": "2451.68690496",
            "4b. close (USD)": "399.12463085",
            "5. volume": "1355809.48649000",
            "6. market cap (USD)": "564862645.54700005"
        },
        "2014-09-14": {
            "1a. open (CNY)": "2962.01679232",
            "1b. open (USD)": "482.07099787",
            "2a. high (CNY)": "2965.10620420",
            "2b. high (USD)": "483.29358801",
            "3a. low (CNY)": "2869.61861068",
            "3b. low (USD)": "467.09377147",
            "4a. close (CNY)": "2922.29135686",
            "4b. close (USD)": "476.17246297",
            "5. volume": "683259.34315800",
            "6. market cap (USD)": "325189068.33300000"
        },
        "2014-09-07": {
            "1a. open (CNY)": "2936.74384437",
            "1b. open (USD)": "477.85654338",
            "2a. high (CNY)": "3028.39207674",
            "2b. high (USD)": "492.96598287",
            "3a. low (CNY)": "2878.05962121",
            "3b. low (USD)": "468.23329399",
            "4a. close (CNY)": "2963.57986560",
            "4b. close (USD)": "482.32538950",
            "5. volume": "748577.21882800",
            "6. market cap (USD)": "358410329.92100000"
        },
        "2014-08-31": {
            "1a. open (CNY)": "3121.95503386",
            "1b. open (USD)": "507.32496043",
            "2a. high (CNY)": "3197.50039779",
            "2b. high (USD)": "520.16776776",
            "3a. low (CNY)": "2926.42935882",
            "3b. low (USD)": "476.34872837",
            "4a. close (CNY)": "2935.82229250",
            "4b. close (USD)": "477.70659172",
            "5. volume": "788373.32211100",
            "6. market cap (USD)": "396032008.39399999"
        },
        "2014-08-24": {
            "1a. open (CNY)": "2984.38540546",
            "1b. open (USD)": "485.32605267",
            "2a. high (CNY)": "3280.72181855",
            "2b. high (USD)": "533.82064425",
            "3a. low (CNY)": "2767.12360828",
            "3b. low (USD)": "450.24203427",
            "4a. close (CNY)": "3121.28623010",
            "4b. close (USD)": "507.21627826",
            "5. volume": "1655897.64805000",
            "6. market cap (USD)": "822999866.53100002"
        },
        "2014-08-17": {
            "1a. open (CNY)": "3642.49657221",
            "1b. open (USD)": "591.70628797",
            "2a. high (CNY)": "3642.94273055",
            "2b. high (USD)": "591.77391745",
            "3a. low (CNY)": "2942.08493896",
            "3b. low (USD)": "478.35061583",
            "4a. close (CNY)": "2988.68222188",
            "4b. close (USD)": "486.02480858",
            "5. volume": "1313739.09357000",
            "6. market cap (USD)": "681531670.18599999"
        },
        "2014-08-10": {
            "1a. open (CNY)": "3619.91026337",
            "1b. open (USD)": "585.99253138",
            "2a. high (CNY)": "3725.90859104",
            "2b. high (USD)": "604.62610213",
            "3a. low (CNY)": "3589.78186696",
            "3b. low (USD)": "581.38883396",
            "4a. close (CNY)": "3640.26572385",
            "4b. close (USD)": "591.34389723",
            "5. volume": "577588.90998000",
            "6. market cap (USD)": "340429067.72399998"
        },
        "2014-08-03": {
            "1a. open (CNY)": "3671.62549301",
            "1b. open (USD)": "593.51430464",
            "2a. high (CNY)": "3694.83413669",
            "2b. high (USD)": "598.35671024",
            "3a. low (CNY)": "3473.44607528",
            "3b. low (USD)": "562.94454230",
            "4a. close (CNY)": "3617.99094831",
            "4b. close (USD)": "585.68183189",
            "5. volume": "877908.15234400",
            "6. market cap (USD)": "513002644.46499997"
        },
        "2014-07-27": {
            "1a. open (CNY)": "3830.47308218",
            "1b. open (USD)": "617.15131748",
            "2a. high (CNY)": "3852.46138271",
            "2b. high (USD)": "621.38608676",
            "3a. low (CNY)": "3661.39538700",
            "3b. low (USD)": "591.86894275",
            "4a. close (CNY)": "3671.43602999",
            "4b. close (USD)": "593.48367815",
            "5. volume": "497928.72969500",
            "6. market cap (USD)": "300824999.54500002"
        },
        "2014-07-20": {
            "1a. open (CNY)": "3854.80866421",
            "1b. open (USD)": "622.29938755",
            "2a. high (CNY)": "3888.36326409",
            "2b. high (USD)": "627.16831317",
            "3a. low (CNY)": "3777.38360963",
            "3b. low (USD)": "609.48643593",
            "4a. close (CNY)": "3829.31833120",
            "4b. close (USD)": "616.96526837",
            "5. volume": "558314.25721700",
            "6. market cap (USD)": "345144434.93199998"
        },
        "2014-07-13": {
            "1a. open (CNY)": "3913.78925409",
            "1b. open (USD)": "630.66025564",
            "2a. high (CNY)": "3915.96945595",
            "2b. high (USD)": "631.82132367",
            "3a. low (CNY)": "3768.10064112",
            "3b. low (USD)": "608.15533259",
            "4a. close (CNY)": "3855.04686174",
            "4b. close (USD)": "622.33784087",
            "5. volume": "661593.83116900",
            "6. market cap (USD)": "411433800.17900002"
        },
        "2014-07-06": {
            "1a. open (CNY)": "3749.16258789",
            "1b. open (USD)": "604.13818935",
            "2a. high (CNY)": "4079.11459961",
            "2b. high (USD)": "658.52085738",
            "3a. low (CNY)": "3734.39445098",
            "3b. low (USD)": "601.75845914",
            "4a. close (CNY)": "3912.06487080",
            "4b. close (USD)": "630.38239193",
            "5. volume": "562653.04864300",
            "6. market cap (USD)": "360013959.94000000"
        },
        "2014-06-29": {
            "1a. open (CNY)": "3774.06238584",
            "1b. open (USD)": "607.49495144",
            "2a. high (CNY)": "3800.81383342",
            "2b. high (USD)": "612.42019230",
            "3a. low (CNY)": "3547.83293850",
            "3b. low (USD)": "570.38637916",
            "4a. close (CNY)": "3748.66260385",
            "4b. close (USD)": "604.05762217",
            "5. volume": "404408.15174400",
            "6. market cap (USD)": "239922581.59099999"
        },
        "2014-06-22": {
            "1a. open (CNY)": "3687.27825346",
            "1b. open (USD)": "594.76374055",
            "2a. high (CNY)": "3832.57941067",
            "2b. high (USD)": "616.69947520",
            "3a. low (CNY)": "3469.12061316",
            "3b. low (USD)": "558.13861583",
            "4a. close (CNY)": "3775.52599070",
            "4b. close (USD)": "607.73054176",
            "5. volume": "398832.17961700",
            "6. market cap (USD)": "240670532.82600001"
        },
        "2014-06-15": {
            "1a. open (CNY)": "4073.54492448",
            "1b. open (USD)": "653.58593457",
            "2a. high (CNY)": "4103.56730552",
            "2b. high (USD)": "660.29079440",
            "3a. low (CNY)": "3511.28035683",
            "3b. low (USD)": "566.21243588",
            "4a. close (CNY)": "3677.85494797",
            "4b. close (USD)": "593.24374666",
            "5. volume": "304380.95443100",
            "6. market cap (USD)": "184730074.60499999"
        },
        "2014-06-08": {
            "1a. open (CNY)": "3997.32387116",
            "1b. open (USD)": "641.41684210",
            "2a. high (CNY)": "4178.27270385",
            "2b. high (USD)": "670.47702721",
            "3a. low (CNY)": "3888.76194698",
            "3b. low (USD)": "623.45960411",
            "4a. close (CNY)": "4073.22117694",
            "4b. close (USD)": "653.53399042",
            "5. volume": "101048.18643900",
            "6. market cap (USD)": "65992007.77340000"
        },
        "2014-06-01": {
            "1a. open (CNY)": "3557.14009356",
            "1b. open (USD)": "571.62427036",
            "2a. high (CNY)": "4181.62294443",
            "2b. high (USD)": "671.01452430",
            "3a. low (CNY)": "3486.86538610",
            "3b. low (USD)": "559.42861091",
            "4a. close (CNY)": "3990.92938595",
            "4b. close (USD)": "640.39077300",
            "5. volume": "99158.81016590",
            "6. market cap (USD)": "59346139.69650000"
        },
        "2014-05-25": {
            "1a. open (CNY)": "2771.55255448",
            "1b. open (USD)": "445.57075132",
            "2a. high (CNY)": "3575.42686047",
            "2b. high (USD)": "574.62662736",
            "3a. low (CNY)": "2752.06850775",
            "3b. low (USD)": "442.21230929",
            "4a. close (CNY)": "3567.89748806",
            "4b. close (USD)": "573.35295903",
            "5. volume": "43921.67012810",
            "6. market cap (USD)": "22923120.97880000"
        },
        "2014-05-18": {
            "1a. open (CNY)": "2704.33124241",
            "1b. open (USD)": "435.20353128",
            "2a. high (CNY)": "2807.30428681",
            "2b. high (USD)": "451.30033986",
            "3a. low (CNY)": "2681.20404558",
            "3b. low (USD)": "431.31928704",
            "4a. close (CNY)": "2773.14761807",
            "4b. close (USD)": "445.82718293",
            "5. volume": "12296.65477500",
            "6. market cap (USD)": "5453826.99222000"
        },
        "2014-05-11": {
            "1a. open (CNY)": "2694.65715186",
            "1b. open (USD)": "431.83289865",
            "2a. high (CNY)": "2830.02320502",
            "2b. high (USD)": "455.45299177",
            "3a. low (CNY)": "2581.58427647",
            "3b. low (USD)": "415.03816353",
            "4a. close (CNY)": "2712.09877980",
            "4b. close (USD)": "436.45354816",
            "5. volume": "17729.29881300",
            "6. market cap (USD)": "7787973.03645000"
        },
        "2014-05-04": {
            "1a. open (CNY)": "2651.02802724",
            "1b. open (USD)": "425.04694983",
            "2a. high (CNY)": "2841.15804217",
            "2b. high (USD)": "455.28183153",
            "3a. low (CNY)": "2582.67284972",
            "3b. low (USD)": "414.20425017",
            "4a. close (CNY)": "2698.52997838",
            "4b. close (USD)": "432.45353935",
            "5. volume": "20886.26380000",
            "6. market cap (USD)": "9218283.46582000"
        },
        "2014-04-27": {
            "1a. open (CNY)": "3092.34750194",
            "1b. open (USD)": "497.76922425",
            "2a. high (CNY)": "3195.51891290",
            "2b. high (USD)": "514.35334520",
            "3a. low (CNY)": "2656.24685512",
            "3b. low (USD)": "425.88369952",
            "4a. close (CNY)": "2662.40213427",
            "4b. close (USD)": "426.87059313",
            "5. volume": "31242.58688700",
            "6. market cap (USD)": "14664184.97190000"
        },
        "2014-04-20": {
            "1a. open (CNY)": "2579.11501210",
            "1b. open (USD)": "415.81580779",
            "2a. high (CNY)": "3422.33483224",
            "2b. high (USD)": "550.80224372",
            "3a. low (CNY)": "2549.81922811",
            "3b. low (USD)": "411.05285485",
            "4a. close (CNY)": "3098.30136865",
            "4b. close (USD)": "498.72760671",
            "5. volume": "54715.76449600",
            "6. market cap (USD)": "27474249.39250000"
        },
        "2014-04-13": {
            "1a. open (CNY)": "2834.99463238",
            "1b. open (USD)": "456.90979993",
            "2a. high (CNY)": "2842.02097930",
            "2b. high (USD)": "458.01512975",
            "3a. low (CNY)": "2234.98738181",
            "3b. low (USD)": "360.24001014",
            "4a. close (CNY)": "2572.23112070",
            "4b. close (USD)": "414.70595777",
            "5. volume": "34788.21625300",
            "6. market cap (USD)": "14476315.48190000"
        }
    }
}